grporlhf/__init__.py
grporlhf/_version.py
grporlhf/cli.py
grporlhf/data_utils.py
grporlhf/trainer.py
grporlhf/utils.py
grporlhf-0.1.0.dist-info/licenses/LICENSE
grporlhf-0.1.0.dist-info/METADATA
grporlhf-0.1.0.dist-info/WHEEL
grporlhf-0.1.0.dist-info/entry_points.txt
grporlhf-0.1.0.dist-info/top_level.txt
grporlhf-0.1.0.dist-info/RECORD
