Metadata-Version: 2.4
Name: grporlhf
Version: 0.1.0
Summary: Reference implementation of Group Relative Policy Optimization (GRPO)
Home-page: https://github.com/kaushikd24/GRPO-Package
Author: Kaushik D. (Not associated with DeepSeek -- Demo Implementation)
Author-email: "Kaushik D." <dwivedi.kaushik24@gmail.com>
License: Apache-2.0
Requires-Python: >=3.9
License-File: LICENSE
Requires-Dist: torch<2.4,>=2.2
Requires-Dist: transformers<4.43,>=4.41.2
Requires-Dist: peft>=0.11.0
Requires-Dist: datasets>=2.20.0
Requires-Dist: pyyaml
Requires-Dist: tqdm
Dynamic: author
Dynamic: home-page
Dynamic: license-file
Dynamic: requires-python
